aim2numpy/__init__.py
aim2numpy/extract.py
aim2numpy-0.2.2.dist-info/METADATA
aim2numpy-0.2.2.dist-info/WHEEL
aim2numpy-0.2.2.dist-info/top_level.txt
aim2numpy-0.2.2.dist-info/RECORD
