Metadata-Version: 2.1
Name: aim2numpy
Version: 0.2.2
Summary: A library to convert Scanco AIM image files to numpy arrays and extract header information
Home-page: https://github.com/Alexhal9000/aim2numpy
Author: Alejandro Gutierrez
Author-email: alejandro.gutierrez@ucalgary.ca
Classifier: Programming Language :: Python :: 3
Classifier: License :: OSI Approved :: MIT License
Classifier: Operating System :: OS Independent
Requires-Python: >=3.6
Requires-Dist: matplotlib
Requires-Dist: numpy
